{"transformations": [{"function": "binarizer", "columns": ["rain"], "numerical_arguments": [], "categorical_arguments": ["uniform", "round"]}, {"function": "apply_math_function", "columns": ["dmc"], "numerical_arguments": [], "categorical_arguments": ["log"]}, {"function": "linear_combination", "columns": ["ffmc", "isi"], "numerical_arguments": [0.5, -0.4], "categorical_arguments": []}, {"function": "create_interaction", "columns": ["temp", "wind"], "numerical_arguments": [], "categorical_arguments": []}, {"function": "standard_scaler", "columns": ["rh"], "numerical_arguments": [], "categorical_arguments": []}, {"function": "apply_math_function", "columns": ["wind"], "numerical_arguments": [], "categorical_arguments": ["square"]}, {"function": "k_bins_discretizer", "columns": ["rh"], "numerical_arguments": [], "categorical_arguments": ["ordinal", "uniform", "quantile", "kmeans"]}, {"function": "subtract_columns", "columns": ["ffmc", "dc"], "numerical_arguments": [], "categorical_arguments": []}, {"function": "normalizer", "columns": ["rain"], "numerical_arguments": [], "categorical_arguments": ["max"]}, {"function": "reduce_dimentionality", "columns": ["temp", "rh", "wind", "ffmc", "dc", "isi"], "numerical_arguments": [], "categorical_arguments": ["PCA"]}]}